{"stages":[
  {"stage":["#######","###+###","# $$.##","#     #","### # #","###   #","#######"],"answer":"DrdrddlluUUdlluRR"},
  {"stage":["#######","##   ##","## # ##","## $ ##","#  * ##","#  + ##","#######"],"answer":"ruuLruulldDDldR"},
  {"stage":["#######","###.$ #","#.$   #","#### ##","##@  ##","#######","#######"],"answer":"rruulLrrruL"},
  {"stage":["#######","#   .##","# $$+##","#  # ##","#    ##","#######","#######"],"answer":"ddlluURlluRR"},
  {"stage":["#######","##  ###","#    ##","#.$$.##","#    ##","##@####","#######"],"answer":"uURuulDrdL"},
  {"stage":["#######","#   ###","# $. ##","## # ##","# *  ##","#@ ####","#######"],"answer":"rUrruululldRD"},
  {"stage":["#######","##  ###","##  ###","#    .#","# $$ @#","# #  .#","#######"],"answer":"dllUUluurDldRRllldRRurDldR"},
  {"stage":["#######","##  ###","##$ ###","#  @ ##","#  $ .#","###  .#","#######"],"answer":"ldRurDldRuuluulDDldRRR"},
  {"stage":["#######","#    ##","#    ##","#* $###","#+  ###","#######","#######"],"answer":"rrUluurrdLulDDrdL"},
  {"stage":["#######","#    ##","#.$* ##","#  # ##","#   @##","#######","#######"],"answer":"uuullDurrdLLulDrrrddllUdrruuullldRddlU"},
  {"stage":["#######","#   .##","# $$ ##","# @####","##.####","#######","#######"],"answer":"luurDDuurrdLullddrUluRR"},
  {"stage":["#######","#   .##","# $$@##","#  # ##","# .  ##","#######","#######"],"answer":"ullDRllddrrruUllD"},
  {"stage":["#######","#   .##","# $$@##","#  # ##","#.   ##","#######","#######"],"answer":"ullDDuurrdLrddlLuUluRR"},
  {"stage":["#######","# .  ##","# $@ ##","# #$.##","#    ##","#######","#######"],"answer":"rddlUUruLdddlluuRRurD"},
  {"stage":["#######","# @ .##","# $$ ##","#  # ##","#   .##","#######","#######"],"answer":"lddrURurDDullluRR"},
  {"stage":["#######","# @ .##","# $$ ##","#  # ##","##.  ##","#######","#######"],"answer":"DDuurrdLullddrUluRR"},
  {"stage":["#######","# @ .##","# $$ ##","#  #.##","#    ##","#######","#######"],"answer":"lddrURurDllluRR"},
  {"stage":["#######","# @$.##","#    ##","# $#.##","#    ##","#######","#######"],"answer":"drruLdllddrUluRRurDllluRR"},
  {"stage":["#######","##   ##","#@$  ##","#. $ ##","#.#  ##","#######","#######"],"answer":"RurrddLLulDruurDrdLL"},
  {"stage":["#######","##  ###","#@$  ##","#.   ##","##.$ ##","#######","#######"],"answer":"RurDrdLLrrdL"},
  {"stage":["#######","#   ###","#  $@##","##$ .##","##  .##","#######","#######"],"answer":"LulldRurDrddllURurDluulldRurDldR"},
  {"stage":["#######","#   ###","# .  ##","##$$ ##","##+ ###","#######","#######"],"answer":"rUruLulldRDrruL"},
  {"stage":["#######","#   ###","#@#  ##","#*$. ##","#    ##","#######","#######"],"answer":"urrdddllURdrruulullD"},
  {"stage":["#######","#.. ###","# @$###","# $  ##","##   ##","#######","#######"],"answer":"ldRdrruLdlUluurrDLdlUrddrruLdlUU"},
  {"stage":["#######","#@  ###","#.$* ##","#  # ##","#    ##","#######","#######"],"answer":"rDlddrrruuLLrrddllUdrruulullDRddlU"},
  {"stage":["#######","#  ####","#  $@##","# *. ##","##   ##","#######","#######"],"answer":"ddllUluurDldRdrruuLrddlluluurD"},
  {"stage":["#######","##@..##","# $$###","#    ##","##   ##","#######","#######"],"answer":"DldRdrruLUluRdlldRdrUU"},
  {"stage":["#######","###  ##","###  ##","#  $*##","#@  .##","#######","#######"],"answer":"rrrULuurDDldlluRR"},
  {"stage":["#######","###.###","###*###","#  $ ##","# @  ##","#######","#######"],"answer":"rruLUddlluRdrU"},
  {"stage":["#######","#   ###","#.#$###","#  @ ##","#. $ ##","###  ##","#######"],"answer":"rddlUruLdlluuurrDDLdlUrrrdLL"},
  {"stage":["#######","#.  ###","#@$$ ##","##   ##","###  ##","####.##","#######"],"answer":"urrDulldRdRluurDrDDlUruLdlUruL"},
  {"stage":["#######","#  ####","#  ####","# @####","# $$ ##","#.  .##","#######"],"answer":"lddrUUddrruLdlluurDldRRululuurDDDrdL"},
  {"stage":["#######","# .####","#  ####","#*@  ##","#  $ ##","#  ####","#######"],"answer":"dlUrrrdLullddrUluRuulDrddrruLdlUU"},
  {"stage":["#######","#. ####","#. ####","#@$  ##","# $  ##","#  ####","#######"],"answer":"dRUrrdLLuluurDldRddlUUUddrrruLLdlU"},
  {"stage":["#######","#.@####","#  ####","# $  ##","# $. ##","#  ####","#######"],"answer":"dlddRUrrdLLuluurDldRdrruLdldlUUUrDldR"},
  {"stage":["#######","## @###","##.$###","##*  ##","#    ##","#   ###","#######"],"answer":"DDrdLdlluRUrrdLdlU"},
  {"stage":["#######","###  ##","#.$$.##","# #  ##","# @  ##","###  ##","#######"],"answer":"ruruulDrddllluuRRurDDulllddrrUruLLrdddrUU"},
  {"stage":["#######","###  ##","###  ##","# *$.##","# #  ##","#   @##","#######"],"answer":"uuulDrddllluuRRllddrrUrULuurD"},
  {"stage":["#######","###+###","#  * ##","# $  ##","## # ##","##   ##","#######"],"answer":"DrdddlluUluRdddrruuLUrdddlluUluR"},
  {"stage":["#######","####.##","####.##","#@$  ##","# $# ##","#    ##","#######"],"answer":"RRllddrrruUUdddllUluRRlddrruU"},
  {"stage":["#######","#     #","# # # #","#. $*@#","#   ###","#######","#######"],"answer":"uulllldddrrUlluurrrrddLLLdlUrrrruullDurrddlLdlluRRuullD"},
  {"stage":["#######","#    .#","# $$  #","###@# #","###  .#","#######","#######"],"answer":"drruuullDulldRRurrdddllUURurDDullluRR"},
  {"stage":["#######","#  # .#","#  $$.#","# #  @#","#    ##","#######","#######"],"answer":"uulDrdLdllluurRRdrUdldlUdlluurRR"},
  {"stage":["#######","#..  ##","# #$  #","#  $  #","#### @#","#######","#######"],"answer":"uululllddrRlluurrrdrddlUlUdrruLuLLrrddlUruL"},
  {"stage":["#######","#@.   #","# $$  #","## # ##","##.  ##","#######","#######"],"answer":"rrrdddlluUluRRldddrruuLulDDurrruLL"},
  {"stage":["#######","#@   ##","# $$  #","# #. .#","#     #","#######","#######"],"answer":"rrDulldRRurDrddllURuulD"},
  {"stage":["#######","#@   ##","# $$ ##","# #. .#","#   ###","#######","#######"],"answer":"rrDulldRRurDlllddrrURuulD"},
  {"stage":["#######","#   ###","#  $  #","##* . #","##   @#","#######","#######"],"answer":"uulLulldRurDrddllURuulD"},
  {"stage":["#######","#  ####","# . . #","# $$#@#","##    #","#######","#######"],"answer":"dlllUdrUlluurDRddlU"},
  {"stage":["#######","##  ..#","##$ # #","#   $ #","#  @###","#######","#######"],"answer":"uuulDrddlluRdrUluurrrddLLUluRRldddlluRdrUUluR"},
  {"stage":["#######","###   #","# $   #","# @$  #","#.. ###","#######","#######"],"answer":"luRRurrdLdLdlluurDrdLurruulDrdLulD"},
  {"stage":["#######","####@.#","#   $*#","#   # #","###   #","#######","#######"],"answer":"rDLLdlluRRddrrUUddlluuR"},
  {"stage":["#######","#     #","# #.  #","#  @$ #","###* ##","###  ##","#######"],"answer":"urrdLLrddlUUruulllddRRdrUruullDDrruL"},
  {"stage":["#######","#  *  #","#     #","## # ##","##$@.##","##   ##","#######"],"answer":"dlUrruulluRdrddllUdrruululldRddrruuruLLrdddlluuRurDDullluR"},
  {"stage":["#######","###  ##","### $ #","### # #","### # #","#..$ @#","#######"],"answer":"lLLrrruuuLulDDDuurrdddlL"},
  {"stage":["#######","#. .  #","#  @  #","##$#  #","#   $ #","#   ###","#######"],"answer":"rdrdLLdlluRUUluRRdrddLdlUUUruLdrrruL"},
  {"stage":["#######","#   .##","# ## ##","#  $$@#","# #   #","#.  ###","#######"],"answer":"dlULddlluuuurrrDulllddddrruuLrdrruLuullldDDurRdrUU"},
  {"stage":["#######","#   ###","# #$$ #","#..  @#","## # ##","##   ##","#######"],"answer":"lllluurrDullddrddrruuruLdddlluuRlluurrDrDLLddrrUdlluururrdLL"},
  {"stage":["#######","#   ###","# #.. #","#     #","##$#$##","## @ ##","#######"],"answer":"lUdrrUUluullddRddrruuruLdddlluuRlddrruU"},
  {"stage":["#######","#   ###","# $   #","##$## #","#.    #","#. @###","#######"],"answer":"urruullulldRDDrdLurrruulLulDDurrrddllL"},
  {"stage":["#######","#   ###","# $   #","##@$  #","##  ###","##..###","#######"],"answer":"RurrdLulDDuuulDDD"},
  {"stage":["#######","#   ###","# @ ###","# $$###","##. . #","##    #","#######"],"answer":"rDulldRddrruLdlUUluurrdDldRuuulDD"},
  {"stage":["#######","#  +###","# $*###","##    #","### # #","###   #","#######"],"answer":"DDrrddllUUlUluR"},
  {"stage":["#######","#  ####","#  # .#","#  $$.#","##   @#","##  ###","#######"],"answer":"uulDrdLLdlUURRdrUlllluurDldRRR"},
  {"stage":["#######","#  ####","# *$.##","#     #","###  @#","###   #","#######"],"answer":"ulllluurDldRRdrruLuLDlluurDldRRurDrddllUUruLdddrUU"},
  {"stage":["#######","#. ####","#.  @##","# # $##","# $   #","###   #","#######"],"answer":"DlddrruLdlUruulllddRRUruLLrddlluUddrrdrruLdlUUruLL"},
  {"stage":["#######","# #####","#.   ##","#.#$$ #","# @   #","#  ####","#######"],"answer":"rUdrruLuLLrDrdLLdlU"},
  {"stage":["#######","##    #","##$ . #","#  @  #","# $#. #","#  ####","#######"],"answer":"llddrUluRRurrddlUruLullDDlddrUluRRluurrdDlluR"},
  {"stage":["#######","##  #.#","##@ #.#","##$   #","#  $  #","#   ###","#######"],"answer":"rdrdLdlluRdrUlURRdrUUdlluulDDrddlluRdrUluRRdrU"},
  {"stage":["#######","## . .#","##$#  #","#     #","# $#  #","# @#  #","#######"],"answer":"UluRRRdrUluullDDlddrUluRRluurrdDrddlUUlluurrrDulllddrrUruLdddrUU"},
  {"stage":["#######","##   ##","##  @ #","# $#. #","# $ .##","#    ##","#######"],"answer":"dddllluRRdrUUruLulldRurDllDldRR"},
  {"stage":["#######","##   ##","## $ ##","# @#  #","#  $  #","####..#","#######"],"answer":"uRurDDDuullddRRurD"},
  {"stage":["#######","###   #","###$$@#","#   ###","#     #","# . . #","#######"],"answer":"ullDDlddrruLuuurrdLulDDDullddrRuulD"},
  {"stage":["#######","##  ###","#   ###","#    .#","# $$ @#","# #  .#","#######"],"answer":"dllUUluurDldRRllldRRurDldR"},
  {"stage":["#######","##  ###","#   ###","#  *$ #","# #.  #","#  @###","#######"],"answer":"uUdrruLLddlluuururDDulldR"},
  {"stage":["#######","##  ###","##   ##","# @$$ #","# # # #","#..   #","#######"],"answer":"urDllddrrUUddrruuLLddlluuRlddrrrruuluLDDullddrRuuuulDrdddlluuRurDrrddLLLrrruullDurrddlL"},
  {"stage":["#######","###   #","#  $# #","#  .$ #","## ##.#","##   @#","#######"],"answer":"uuLLrrddllluUrrruullDurrddddllluuRRluurrdDlllluRdrrruullD"},
  {"stage":["#######","###   #","#  .@ #","# $$  #","##. ###","##  ###","#######"],"answer":"llDRddlUruulldRdrUluRurrddLLulDrrruL"},
  {"stage":["#######","###   #","##@$$ #","##.#  #","#     #","#.  ###","#######"],"answer":"ddrruruulDDrdLLdlluRuuRurDrddlLdlUrrruulllDDrdLuuurrDrdLLdlU"},
  {"stage":["#######","###  ##","#  $@##","#  $ ##","###   #","### ..#","#######"],"answer":"LDlluRRdrddlUruLulldRururDDDldRuuulldRurDD"},
  {"stage":["#######","###  ##","#  *@##","#  $.##","###   #","###   #","#######"],"answer":"LDlluRRdrddlUruLulldRururDDulldRddrruLdlUU"},
  {"stage":["#######","###  ##","#@ .$##","#   $ #","# #.  #","#     #","#######"],"answer":"drrdrruLddllluuurrDrddlUdlluuurrurDDrddlluUrrdL"},
  {"stage":["#######","###  ##","###  ##","#  *$ #","# #.# #","#    @#","#######"],"answer":"lluUddrruuLLruulDDrrddlllluuR"},
  {"stage":["#######","###  ##","###  ##","#   @##","# *$. #","###   #","#######"],"answer":"ddlUUlldRRuruulDrdLdlluRRddrruLLuurD"},
  {"stage":["#######","###  ##","###  ##","#  $$##","# . . #","###  @#","#######"],"answer":"ulULuurDDldlluRRddrruLLuurD"},
  {"stage":["#######","###  ##","###.$##","#@  $ #","# #.  #","#   ###","#######"],"answer":"rrdrruLLuurDDlddlluuRlddrruUrrdL"},
  {"stage":["#######","##   ##","#+ # ##","# $   #","#.$ # #","###   #","#######"],"answer":"ddRluururrddlLdlUrrrrddllUdrruulLruulldDrdL"},
  {"stage":["#######","####..#","#     #","# $$ @#","##  ###","##  ###","#######"],"answer":"ulllDRddlUUrurrdLulDlluRRRlldddrUUluRdrUdrU"},
  {"stage":["#######","##   ##","# #.$ #","# .*  #","#   $ #","##  @##","#######"],"answer":"URUULDRDLLDLU"},
  {"stage":["#######","###  ##","##@$.##","# $$  #","# . . #","###   #","#######"],"answer":"DURURDDRDDLLUULUR"},
  {"stage":["#######","##   ##","# #+$ #","# .*  #","#   $ #","##   ##","#######"],"answer":"URDRDDLLDLURRURUL"},
  {"stage":["#######","###.  #","###   #","# $*$ #","#   ###","#@ .###","#######"],"answer":"URRUURRDLULDDLLUR"},
  {"stage":["#######","#  .###","# $*###","## .$ #","### # #","### @ #","#######"],"answer":"LUULULURDDRDDRRUUL"},
  {"stage":["#######","# #####","#..  ##","#*#$$ #","# @   #","#  ####","#######"],"answer":"RUDRRULULLRRDDLURUL"},
  {"stage":["#######","##   ##","# #.  #","#@*.  #","# $$  #","##   ##","#######"],"answer":"RRURRDDLURULDDDLLUDRU"},
  {"stage":["#######","###  ##","##@$.##","# $$  #","# . . #","###   #","#######"],"answer":"RLDLDRRLURDDRRUULLULD"},
  {"stage":["#######","###@###","#  $###","#$#   #","#.# # #","##.*  #","#######"],"answer":"DDULLDURRDRRDDLLRRUULLD"},
  {"stage":["#######","## @###","##$$###","#    ##","#   ..#","### $.#","#######"],"answer":"LDDLDRRRLDRUULLUURDDLDR"},
  {"stage":["#######","#     #","#  .# #","# $.$ #","# #.$ #","#    @#","#######"],"answer":"LLLLUURLDDRRUUDDRRUULRDL"},
  {"stage":["#######","#     #","# *.@ #","##$*  #","##  ###","##  ###","#######"],"answer":"ULLLDRRLDRDDLUURUURRDLRDL"},
  {"stage":["#######","##   ##","## # ##","## $  #","#.*$# #","##.@  #","#######"],"answer":"RRUULLDURRDDLLULRURUULLDD"},
  {"stage":["#######","##  ###","#    ##","# *+$ #","## *  #","##   ##","#######"],"answer":"ULLDRDDRRULULUURDRDRDLDLLU"},
  {"stage":["#######","###   #","##  $@#","#. $ ##","#.$ ###","#. ####","#######"],"answer":"LDLDLRURUULDLDLDURURRDLLRDL"},
  {"stage":["#######","##@  ##","#  #  #","# $*$ #","#  .  #","## . ##","#######"],"answer":"DDLDRUUURRDDLDLLURUURRDDRDL"},
  {"stage":["#######","#  @###","# ..$ #","# .#$ #","#  $  #","##   ##","#######"],"answer":"DLDDDRRURUULLRRDDLURULDDLDLU"},
  {"stage":["#######","##  ###","## $$ #","##... #","#  @$ #","#   ###","#######"],"answer":"URRDLULLUURDLDRLDDRURRUULLULD"},
  {"stage":["#######","##  ###","# .$  #","#@.$  #","# .$ ##","##  ###","#######"],"answer":"RRLDDRURULDLLUURURDDRDLURRULL"},
  {"stage":["#######","#   ###","# $   #","##@$  #","##.$###","##..###","#######"],"answer":"RURRDLLDUUULLDRURDLDDUURRDLULD"},
  {"stage":["#######","###   #","## *  #","# .@$##","#  *  #","###   #","#######"],"answer":"LURDLDRDRRULDLULUURURRDLDLDDRRUL"},
  {"stage":["#######","###.###","#  *  #","# #*# #","#  $  #","## @ ##","#######"],"answer":"RURUULLRRDDLDLLURUURRDDLDLULLUUR"},
  {"stage":["#######","####  #","# @#  #","# $.$ #","# *.  #","##  ###","#######"],"answer":"LDDRDRURUDLLLUURDRDRRULRUULDDRDL"},
  {"stage":["#######","#@    #","#  $  #","##$*.##","## .###","##  ###","#######"],"answer":"DRDURLDRDDLUURUULLDRURDDUURRDLULD"},
  {"stage":["#######","##  ###","## $$ #","##... #","#  @$ #","#   ###","#######"],"answer":"URRDLULLDDRULURLUURDLDDRRRUULLULD"},
  {"stage":["#######","#   ###","# # ###","#*.$  #","#  #$ #","#@   .#","#######"],"answer":"RRRRUULLRDULUULLDDRDDRRLLLUDRRRUUL"},
  {"stage":["#######","##  . #","# . $ #","# .$  #","#   $##","## @ ##","#######"],"answer":"ULUUURRRDDLULLDDRURULDDDRULUURRDLL"},
  {"stage":["#######","###.###","# $$.##","#   . #","###$# #","###@  #","#######"],"answer":"RRUULLUDLLURRDRRDDLLUDRRUULLULLDRR"},
  {"stage":["#######","##  ###","#     #","#.**$@#","#   ###","##  ###","#######"],"answer":"ULLDULLDDRURURRDLLLDDRULURUULDRRRDL"},
  {"stage":["#######","## .###","#  $  #","#.    #","###$*##","###@ ##","#######"],"answer":"UDRUULLUURDDRRULDLUDRDDLURUULLDRURD"},
  {"stage":["#######","#     #","# #@# #","# $$$ #","##  . #","####..#","#######"],"answer":"DUULLDDRDRLULUURRDDRLUURRDDDULDULLDR"},
  {"stage":["#######","##  ###","#     #","#.**$@#","#   ###","##  ###","#######"],"answer":"ULLDULLDDRURURRDLLLDDRULURURRDLULULD"},
  {"stage":["#######","##  ###","## * ##","# .@$ #","#  *  #","#  #  #","#######"],"answer":"LUURDRDLULDRRRDDLURULULLDLDDRURURRDL"},
  {"stage":["#######","#  +$ #","# #.# #","#     #","#* $ ##","#  ####","#######"],"answer":"DDLDDLUURRRDLULLDDRURUUULLDDRDRURRUUL"},
  {"stage":["#######","##   ##","## #.##","#  $.##","# # $ #","#  * @#","#######"],"answer":"LLRRULUUULLDDRLLDDRRURUDLDLLUURRDRRDL"},
  {"stage":["#######","#    ##","# #  ##","#  $$##","#  $@.#","### ..#","#######"],"answer":"LULLUURRDRDDLDRUUUULLLDDRRURDDULLLDRRR"},
  {"stage":["#######","#@ ..##","# #$ ##","# #   #","#  $# #","#  *  #","#######"],"answer":"RRRDDLUDRRDDLLUUDLLUUURRLLDDDRRUUDDLLDR"},
  {"stage":["#######","###@  #","#  $. #","#  $. #","## $ ##","### .##","#######"],"answer":"RDDLRDDLULURDRURUULDDDUUULDRDDLLURLLURR"},
  {"stage":["#######","###   #","###$+.#","#  $$.#","#    ##","###  ##","#######"],"answer":"DLDLLURRRUULDRDLDLLURDRDRUUDLLURURLDDRU"},
  {"stage":["#######","###@ ##","#  $$##","# #$ .#","#   ..#","###  ##","#######"],"answer":"RDLDRDDLULLUURRURDDULLLDDRRRUULDULLDDRR"},
  {"stage":["#######","#   ###","#   ###","## $  #","#+**# #","#     #","#######"],"answer":"DRRRRUULLRRDDLLULUDDRRRUULLUULLDRURDDULD"},
  {"stage":["#######","##   ##","##   ##","###  ##","# $$$ #","# .+. #","#######"],"answer":"UURDLDLLURDRURUUULLDRDRDRDLLRUULDUUURDDD"},
  {"stage":["#######","###   #","#@*$. #","# $  .#","###  ##","###  ##","#######"],"answer":"DRRRUULDDLLURRDRDDLURULULLDRRUURRDLLDDRU"},
  {"stage":["#######","#  . @#","# #.# #","#   $ #","#.$$ ##","#   ###","#######"],"answer":"LLDDLLDDRRUULLUURRRRDDLLUDDDLLUURLDDRRUUDL"},
  {"stage":["#######","###@  #","#  *  #","# $ *.#","###  ##","###  ##","#######"],"answer":"RDDLDDRUURUULLDDULLDRRRDDLURULULLDRRUURRDL"},
  {"stage":["#######","#. #  #","#  $  #","#. $#@#","#  $  #","#. #  #","#######"],"answer":"DLLRRUULLDULDLUDDDRULUURRRRDDLLLRUULLDDRRUL"},
  {"stage":["#######","###@  #","# .$  #","#  $..#","### $##","###  ##","#######"],"answer":"RDDLDDRUURUULLDDULLDRRRDDLURULULLDRRUURRDLL"},
  {"stage":["#######","##  .##","## #$##","# $  ##","# # $.#","# .  @#","#######"],"answer":"LLLLUURLDDRRRRULDLLLUURUURRDDUULLDDRDRUUDDDL"},
  {"stage":["#######","#  ####","#.*$  #","# .$# #","## @  #","##   ##","#######"],"answer":"LULUURDRDULLDRDDRRURUULLLDDDRRULDLURUDRRUULL"},
  {"stage":["#######","###@  #","#     #","# *$.##","# $  ##","# .####","#######"],"answer":"DLLDDRULURRURRDLLRDDLULDURRUULDRDLDLLUURRURD"},
  {"stage":["#######","#  ####","#.*$  #","# .$# #","## @  #","##   ##","#######"],"answer":"LULUURDRDULLDRDDRRULDLURRRUULLLRRRDDLLUDRRUULL"},
  {"stage":["#######","#  #  #","#  #  #","# $$  #","#@ .$##","###..##","#######"],"answer":"RRDRUURUULDDDLLLUURDLDRURDRURUULDRDLLDLLUURDLDR"},
  {"stage":["#######","#  . ##","# #. ##","#  .  #","# $$$ #","#  # @#","#######"],"answer":"UULLLLDDRULURLUURRDRDRDDLULUUDLLDDRULURDRUDRRUL"},
  {"stage":["#######","#   ###","#.   ##","# #.$ #","# $$# #","##@.  #","#######"],"answer":"RUUDDRRUULULDDUUULLDDDRDRULLUUURRDRDRDDLRUULULL"},
  {"stage":["#######","#  .###","# #. ##","#  .  #","# $$$ #","#  # @#","#######"],"answer":"UULLLLDDRULURLUURRDRDRDDLULUUDLLDDRULURDRUDRRUL"},
  {"stage":["#######","###   #","## $+.#","#  $$.#","#  # ##","#    ##","#######"],"answer":"DLRUULDLDRRLLLDDRULURDDRRUUDDLLUUURRLLDRLDDRRUU"},
  {"stage":["#######","###  ##","## . ##","# $*$ #","# #.  #","#  @  #","#######"],"answer":"UUDDLLUURURDLLDDRRRURULLUURDDRDDLLUURRDLDLLLUUR"},
  {"stage":["#######","#   ..#","# $ @.#","##$$  #","##  ###","##  ###","#######"],"answer":"ULLLDRRURRDDLULURDLLDRDDLUUULURRDRRDLULLDDRULURR"},
  {"stage":["#######","#   ###","#   $ #","##$*  #","## ..##","##@ ###","#######"],"answer":"URRURULLULLDRDRLUURDRDULLDRDDLUURUULLDRURDDURRDL"},
  {"stage":["#######","#    ##","# ## ##","# .$@.#","## $$ #","##  #.#","#######"],"answer":"UULLLDDRRLDDRURUDLLULUURRRDDRDLLRUUULLLDDRRRDLDLU"},
  {"stage":["#######","#@  ###","# $$$ #","## ...#","##  # #","##    #","#######"],"answer":"RRDULLDRDRLUURDDLDDRRRUUULLULLDRDRRLLDDRULURLUURD"},
  {"stage":["#######","#... ##","# $ $ #","##    #","##$  ##","##@####","#######"],"answer":"URURRULULDULLDRURRDDDLLUUDDRRUUULLRRDLRDDLLUUDDRUU"},
  {"stage":["#######","##   ##","## .  #","## *  #","# $* ##","#  @###","#######"],"answer":"LUURURRDLUULLDRRDDLUDDLLURDRURUUULLDDUURRDDDLDLLUR"},
  {"stage":["#######","###  ##","# +* ##","# #$  #","#   # #","#   * #","#######"],"answer":"RDRRDDLLULLUURRURDLLLDDRRUDDRRUULULRDRDDLLUUDLLDRR"},
  {"stage":["#######","#   . #","# # # #","# $@$ #","# # #.#","#  *  #","#######"],"answer":"UULLDDRLUURRRRDDDDLLUURLLLUURRRRDDLLUDLLUURRDDLLDDR"},
  {"stage":["#######","#  ####","#  #  #","#.$**@#","##    #","##   ##","#######"],"answer":"DLLLUDRRRUULDRDLDLLUURLLUURDLDRDDRRURUULDLLDDRRUDLU"},
  {"stage":["#######","# . ###","# ..#@#","## $  #","##$#$ #","##    #","#######"],"answer":"DDDLLLUUDDRRRUULLUULLDRDRRRDDLLLUUUDDDRRURULLRDDLLUU"},
  {"stage":["#######","##  ###","#  $###","# .$  #","# .*  #","###@  #","#######"],"answer":"RUULRDDLULLUURDLDRRDRRUULLDLLUURDUURDLDRDDRRUULLRRDL"},
  {"stage":["#######","#  ####","#   ###","#$ $@##","#. #$ #","#  . .#","#######"],"answer":"LULLDURRDRDULULLDRDDRRUULULDRRDDLLLUDRRRUULLDLDRUUULD"},
  {"stage":["#######","# .   #","# . $ #","##.#$ #","##@ $ #","###  ##","#######"],"answer":"UUURRRDLLRRDDLUULULLDRDDRDRURUULLULDRRRULLDRRDDLURULL"},
  {"stage":["#######","#. #  #","#  $  #","#. $#@#","#  $  #","#. #  #","#######"],"answer":"ULLLDLURRRRDDLLRRUULLLDLDDRULUURRDURRDDLLLRUULLDDRRUL"},
  {"stage":["#######","#    ##","# #. ##","#  $$ #","###*+ #","###   #","#######"],"answer":"ULUULLDDRLUURRRDDLRRDDLLUURUULLLDDRRDDRRULULLLUURRRDD"},
  {"stage":["#######","#@ . ##","#  $  #","# #*# #","#  $  #","## . ##","#######"],"answer":"RRRDLULLDDDRRUURULDRRDDLRUULLDDLLUURLDDRRRRUULULDLLUR"},
  {"stage":["#######","#   ###","# $@  #","##* . #","# * # #","#     #","#######"],"answer":"ULLDRURDRDRDDLLLLURDRRRUUULLLDRURRDDDLLUUDDRRUUULLULD"},
  {"stage":["#######","###  ##","## $@.#","## **##","#    ##","#    ##","#######"],"answer":"DLRUULDLDURRDLDDLLURDRRUULURLLDRRDDLURUULLDRDDLLURDRU"},
  {"stage":["#######","####  #","#@$ $.#","##   .#","## #$.#","##   ##","#######"],"answer":"RDDDRRURULRUULDRDDLDLLUUURRURDDULLLDDDRRUUDDLLUURRLUR"},
  {"stage":["#######","#####.#","###@ .#","###$$.#","#   $ #","#    ##","#######"],"answer":"RRDDLLRRUULLDRDRUUDDLDLUDLLURRDRURUULLDRDDLLURDRUULUR"},
  {"stage":["#######","#  ####","#  $ ##","# $*. #","##. # #","##@   #","#######"],"answer":"UULUURDDRDDRRUULULDLLUURDLDRURRDRDDLLLUURLDDRULULUURDD"},
  {"stage":["#######","#. @  #","#$#$# #","# $  .#","# # # #","# .   #","#######"],"answer":"RRDDDDLLLLUUUDDDRRUURRUULLDDRRDDLLLLUURRDUUURRDDDDLLUUR"},
  {"stage":["#######","###@ .#","#. $  #","#   $ #","### *##","###  ##","#######"],"answer":"RDLDLLURRURRDDLLRULURDDLDDRUULULLDRURDRDDLURURULLLDRURD"},
  {"stage":["#######","#     #","# .#  #","##*   #","# *$ ##","#@  ###","#######"],"answer":"RRUDLLURURLDDRURURUULLLDDUURRRDDLLDDLLURURRDLURRUULDRDLL"},
  {"stage":["#######","# . *@#","#  #$ #","#  .  #","##  $##","##   ##","#######"],"answer":"LLRRDDLLLULURRLDDRRRUULDRDLLDLULUURDLDRDDRRUURUULLRRDDLU"},
  {"stage":["#######","##  # #","##  ###","##$.  #","#  *  #","# .$@ #","#######"],"answer":"LULURUULDRDDLLDRRUUULDRDRRULDLUDDLLURRURRDLRDLLRUULLUURD"},
  {"stage":["#######","##   ##","##..$##","#  .  #","#  $$ #","####@ #","#######"],"answer":"URULDLULUURRDULLDDRDRRULUULLDDLDRRLUUURRDDLDLURRRDDLURUL"},
  {"stage":["#######","# + * #","# $#  #","#  .  #","##$  ##","##   ##","#######"],"answer":"DLDRRDRURUULLRRDDLLLULURDDRDDLUURRRUULDRDLDLLULUURRLLDDRU"},
  {"stage":["#######","##  ###","##    #","# $. .#","# #$$ #","#@ .###","#######"],"answer":"RRUUDDLLUURURLDLDDRRUURRDLULDULUURDLDRDRRUULRDDLLURLLUURD"},
  {"stage":["#######","#+. ###","#.$$ ##","## $  #","## #  #","##    #","#######"],"answer":"RDDRLUURDRDRDDLLLUUURULDRRDLRRDDLLLUUUDDDRRURULLRDDLLUURUL"},
  {"stage":["#######","#  ####","# ..  #","# .@$ #","## $$ #","####  #","#######"],"answer":"URRDLLRRDDLUULULLDRDRLUURDRRDDLURUULLDLDRUURRDLLRRDDLUURUL"}
]}